chisel3/test_run_dir/SqueezeFunctionalityTester/202203291506352452759517212920665/SqueezeFunctionalityTester.v
module SqueezeFunctionalityTester(
  input   clock,
  input   reset
);
`ifdef RANDOMIZE_REG_INIT
  reg [31:0] _RAND_0;
`endif // RANDOMIZE_REG_INIT
  reg [9:0] counter; // @[IntervalSpec.scala 230:24]
  wire [9:0] _counter_T_1 = counter + 10'h1; // @[IntervalSpec.scala 231:22]
  wire  _T = counter > 10'ha; // @[IntervalSpec.scala 232:16]
  wire  _T_2 = ~reset; // @[IntervalSpec.scala 233:9]
  wire [9:0] _GEN_0 = counter; // @[IntervalSpec.scala 243:{37,37}]
  wire [3:0] _toSqueeze_T = _GEN_0[3:0]; // @[IntervalSpec.scala 243:{37,37}]
  wire [4:0] _GEN_2 = $signed(_toSqueeze_T) - 4'sh6; // @[IntervalSpec.scala 243:{45,45}]
  wire [3:0] toSqueeze = _GEN_2[3:0]; // @[IntervalSpec.scala 243:{45,45}]
  wire [3:0] squeezeTemplate = _GEN_2[3:0]; // @[IntervalSpec.scala 245:{39,39}]
  always @(posedge clock) begin
    if (reset) begin // @[IntervalSpec.scala 230:24]
      counter <= 10'h0; // @[IntervalSpec.scala 230:24]
    end else begin
      counter <= _counter_T_1; // @[IntervalSpec.scala 231:11]
    end
    `ifndef SYNTHESIS
    `ifdef STOP_COND
      if (`STOP_COND) begin
    `endif
        if (_T & ~reset) begin
          $finish; // @[IntervalSpec.scala 233:9]
        end
    `ifdef STOP_COND
      end
    `endif
    `endif // SYNTHESIS
    `ifndef SYNTHESIS
    `ifdef PRINTF_COND
      if (`PRINTF_COND) begin
    `endif
        if (_T_2) begin
          $fwrite(32'h80000002,"SqueezeTest %d    %d.squeeze(range\"[-2,5].0\") => %d\n",counter,toSqueeze,
            squeezeTemplate); // @[IntervalSpec.scala 247:9]
        end
    `ifdef PRINTF_COND
      end
    `endif
    `endif // SYNTHESIS
  end
// Register and memory initialization
`ifdef RANDOMIZE_GARBAGE_ASSIGN
`define RANDOMIZE
`endif
`ifdef RANDOMIZE_INVALID_ASSIGN
`define RANDOMIZE
`endif
`ifdef RANDOMIZE_REG_INIT
`define RANDOMIZE
`endif
`ifdef RANDOMIZE_MEM_INIT
`define RANDOMIZE
`endif
`ifndef RANDOM
`define RANDOM $random
`endif
`ifdef RANDOMIZE_MEM_INIT
  integer initvar;
`endif
`ifndef SYNTHESIS
`ifdef FIRRTL_BEFORE_INITIAL
`FIRRTL_BEFORE_INITIAL
`endif
initial begin
  `ifdef RANDOMIZE
    `ifdef INIT_RANDOM
      `INIT_RANDOM
    `endif
    `ifndef VERILATOR
      `ifdef RANDOMIZE_DELAY
        #`RANDOMIZE_DELAY begin end
      `else
        #0.002 begin end
      `endif
    `endif
`ifdef RANDOMIZE_REG_INIT
  _RAND_0 = {1{`RANDOM}};
  counter = _RAND_0[9:0];
`endif // RANDOMIZE_REG_INIT
  `endif // RANDOMIZE
end // initial
`ifdef FIRRTL_AFTER_INITIAL
`FIRRTL_AFTER_INITIAL
`endif
`endif // SYNTHESIS
endmodule

chisel3/test_run_dir/SqueezeFunctionalityTester/202203291506352452759517212920665/dump.vcd
$version Generated by VerilatedVcd $end
$date Tue Mar 29 15:06:51 2022 $end
$timescale 1ps $end

 $scope module TOP $end
  $var wire  1 # clock $end
  $var wire  1 $ reset $end
  $scope module SqueezeFunctionalityTester $end
   $var wire  1 # clock $end
   $var wire 10 % counter [9:0] $end
   $var wire  1 $ reset $end
   $var wire  4 & squeezeTemplate [3:0] $end
   $var wire  4 & toSqueeze [3:0] $end
  $upscope $end
 $upscope $end
$enddefinitions $end


#0
0#
1$
b0000000000 %
b1010 &
#1
1#
#2
#3
#4
#5
#6
0#
#7
#8
#9
#10
0$
#11
1#
b0000000001 %
b1011 &
#12
#13
#14
#15
#16
0#
#17
#18
#19
#20
#21
1#
b0000000010 %
b1100 &
#22
#23
#24
#25
#26
0#
#27
#28
#29
#30
#31
1#
b0000000011 %
b1101 &
#32
#33
#34
#35
#36
0#
#37
#38
#39
#40
#41
1#
b0000000100 %
b1110 &
#42
#43
#44
#45
#46
0#
#47
#48
#49
#50
#51
1#
b0000000101 %
b1111 &
#52
#53
#54
#55
#56
0#
#57
#58
#59
#60
#61
1#
b0000000110 %
b0000 &
#62
#63
#64
#65
#66
0#
#67
#68
#69
#70
#71
1#
b0000000111 %
b0001 &
#72
#73
#74
#75
#76
0#
#77
#78
#79
#80
#81
1#
b0000001000 %
b0010 &
#82
#83
#84
#85
#86
0#
#87
#88
#89
#90
#91
1#
b0000001001 %
b0011 &
#92
#93
#94
#95
#96
0#
#97
#98
#99
#100
#101
1#
b0000001010 %
b0100 &
#102
#103
#104
#105
#106
0#
#107
#108
#109
#110
#111
1#
b0000001011 %
b0101 &
